setup.py
shortid/short_id.py
shortid8.egg-info/PKG-INFO
shortid8.egg-info/SOURCES.txt
shortid8.egg-info/dependency_links.txt
shortid8.egg-info/top_level.txt