Metadata-Version: 1.0
Name: shortid8
Version: 1.0
Summary: 根据uuid生成不重复的8位短id
Home-page: https://github.com/newpanjing/shortid
Author: shortid
Author-email: newpanjing@icloud.com
License: Apache Licene 2.0
Platform: any
